AUTHORS
LICENSE
MANIFEST.in
setup.py
Flask_Email.egg-info/PKG-INFO
Flask_Email.egg-info/SOURCES.txt
Flask_Email.egg-info/dependency_links.txt
Flask_Email.egg-info/not-zip-safe
Flask_Email.egg-info/requires.txt
Flask_Email.egg-info/top_level.txt
docs/Makefile
docs/conf.py
docs/index.rst
docs/make.bat
docs/_themes/.gitignore
docs/_themes/LICENSE
docs/_themes/README
docs/_themes/flask_theme_support.py
docs/_themes/flask/layout.html
docs/_themes/flask/relations.html
docs/_themes/flask/theme.conf
docs/_themes/flask/static/flasky.css_t
docs/_themes/flask/static/small_flask.css
docs/_themes/flask_small/layout.html
docs/_themes/flask_small/theme.conf
docs/_themes/flask_small/static/flasky.css_t
flask_email/__init__.py
flask_email/encoding.py
flask_email/message.py
flask_email/signals.py
flask_email/utils.py
flask_email/backends/__init__.py
flask_email/backends/base.py
flask_email/backends/console.py
flask_email/backends/dummy.py
flask_email/backends/filebased.py
flask_email/backends/locmem.py
flask_email/backends/smtp.py
flask_email/backends/rest/__init__.py
flask_email/backends/rest/concurrent.py
flask_email/contrib/__init__.py
flask_email/contrib/mailgun/__init__.py
flask_email/contrib/mailgun/rest/__init__.py
flask_email/contrib/mailgun/rest/concurrent.py
tests/__init__.py
tests/console.py
tests/dummy.py
tests/filebased.py
tests/locmem.py
tests/messages.py
tests/rest.py
tests/smtp.py