Metadata-Version: 1.1
Name: Flask-Email
Version: 1.4.3
Summary: Flask extension for sending email
Home-page: https://github.com/allanlei/flask-email
Author: Allan Lei
Author-email: allanlei@helveticode.com
License: BSD
Platform: any
Classifier: Environment :: Web Environment
Classifier: Intended Audience :: Developers
Classifier: License :: OSI Approved :: BSD License
Classifier: Operating System :: OS Independent
Classifier: Programming Language :: Python
Classifier: Topic :: Internet :: WWW/HTTP :: Dynamic Content
Classifier: Topic :: Software Development :: Libraries :: Python Modules
